sl_dbserver-0.0.0-py3.10-nspkg.pth
sl/dbserver/__init__.py
sl/dbserver/_test_app.py
sl/dbserver/_test_db.py
sl/dbserver/app.py
sl/dbserver/cli.py
sl/dbserver/conftest.py
sl/dbserver/db.py
sl/dbserver/types.py
sl/dbserver/__test__/__init__.py
sl/dbserver/__test__/fixtures.py
sl/dbserver/__test__/db/__init__.py
sl/dbserver/__test__/db/models.py
sl/dbserver/util/__init__.py
sl/dbserver/util/_test_file.py
sl/dbserver/util/file.py
sl/dbserver/util/db/__init__.py
sl/dbserver/util/db/_test_url.py
sl/dbserver/util/db/conn.py
sl/dbserver/util/db/schema.py
sl/dbserver/util/db/seed.py
sl/dbserver/util/db/serialize.py
sl/dbserver/util/db/url.py
sl_dbserver-0.0.0.dist-info/LICENSE.md
sl_dbserver-0.0.0.dist-info/METADATA
sl_dbserver-0.0.0.dist-info/WHEEL
sl_dbserver-0.0.0.dist-info/entry_points.txt
sl_dbserver-0.0.0.dist-info/namespace_packages.txt
sl_dbserver-0.0.0.dist-info/top_level.txt
sl_dbserver-0.0.0.dist-info/RECORD
