Metadata-Version: 2.1
Name: sl-dbserver
Version: 0.0.0
Summary: Springless Database Server
Home-page: https://github.com/Springless/sl-dbserver
Author: cogs
Author-email: cogs@springless.com
License: MIT
Keywords: sl springless database server testing postgresql
Classifier: Programming Language :: Python :: 3
Classifier: Topic :: Internet :: WWW/HTTP
Classifier: Topic :: Software Development :: Testing
License-File: LICENSE.md
Requires-Dist: sqlalchemy[asyncio] (<2,>=1)
Requires-Dist: python-dateutil (>=2)
Requires-Dist: sqlalchemy-utils
Requires-Dist: psycopg2-binary (>=2)
Requires-Dist: python-slugify (>=4)
Requires-Dist: fastapi[all]
Requires-Dist: uvicorn[standard]
Provides-Extra: dev
Requires-Dist: pytest (>=7) ; extra == 'dev'
Requires-Dist: pytest-cov (>=4) ; extra == 'dev'
Requires-Dist: pytest-asyncio (>=0.17) ; extra == 'dev'
Requires-Dist: mypy (>=0.812) ; extra == 'dev'
Requires-Dist: requests (<3,>=2) ; extra == 'dev'
Requires-Dist: types-python-dateutil (<3,>=2) ; extra == 'dev'
Requires-Dist: black (>=23) ; extra == 'dev'
Requires-Dist: alembic (>=1) ; extra == 'dev'
Requires-Dist: build ; extra == 'dev'
Requires-Dist: twine ; extra == 'dev'
